COPYING.txt
README.txt
ROADMAP.txt
SCHEMA-PREAMBLE.txt
setup.cfg
setup.py
Schevo.egg-info/PKG-INFO
Schevo.egg-info/SOURCES.txt
Schevo.egg-info/dependency_links.txt
Schevo.egg-info/entry_points.txt
Schevo.egg-info/not-zip-safe
Schevo.egg-info/requires.txt
Schevo.egg-info/top_level.txt
doc/SchevoGettingStarted.txt
doc/SchevoGettingStartedMacOsx.txt
doc/SchevoGettingStartedUbuntu.txt
doc/SchevoGettingStartedWindows.txt
doc/SchevoTutorialMovieReviews1.txt
doc/SchevoTutorials.txt
doc/__init__.py
schevo/__init__.py
schevo/base.py
schevo/change.py
schevo/constant.py
schevo/database.py
schevo/entity.py
schevo/error.py
schevo/extent.py
schevo/field.py
schevo/fieldspec.py
schevo/label.py
schevo/meta.py
schevo/namespace.py
schevo/query.py
schevo/schema.py
schevo/signal.py
schevo/template.py
schevo/trace.py
schevo/transaction.py
schevo/view.py
schevo/store/_persistent.c
schevo/example/__init__.py
schevo/example/todo/__init__.py
schevo/example/todo/icons/db.Gender.png
schevo/example/todo/icons/db.Item.png
schevo/example/todo/icons/db.Person.png
schevo/example/todo/icons/db.Priority.png
schevo/example/todo/icons/db.SchevoIcon.png
schevo/example/todo/icons/db.Topic.png
schevo/example/todo/schema/__init__.py
schevo/example/todo/schema/schema_001.py
schevo/example/videostore/__init__.py
schevo/example/videostore/schema/__init__.py
schevo/example/videostore/schema/schema_001.py
schevo/icon/__init__.py
schevo/icon/_build.py
schevo/icon/_default_png.py
schevo/icon/default.png
schevo/icon/plugin.py
schevo/icon/schema/__init__.py
schevo/icon/schema/schema_001.py
schevo/identity/__init__.py
schevo/identity/schema/__init__.py
schevo/identity/schema/schema_001.py
schevo/lib/__init__.py
schevo/lib/module.py
schevo/lib/odict.py
schevo/lib/optimize.py
schevo/mt/__init__.py
schevo/mt/mrow.py
schevo/mt/plugin.py
schevo/script/__init__.py
schevo/script/command.py
schevo/script/db.py
schevo/script/db_create.py
schevo/script/db_evolve.py
schevo/script/db_inject.py
schevo/script/db_update.py
schevo/script/main.py
schevo/script/opt.py
schevo/script/path.py
schevo/script/shell.py
schevo/store/ACKS.txt
schevo/store/CHANGES.txt
