Metadata-Version: 1.0
Name: Schevo
Version: 3.0
Summary: Next-generation DBMS
Home-page: http://schevo.org/wiki/Schevo
Author: Orbtech, L.L.C. and contributors
Author-email: schevo@googlegroups.com
License: LGPL
Keywords: database dbms
Platform: UNIX
Platform: Windows
Classifier: Development Status :: 4 - Beta
Classifier: Environment :: Console
Classifier: Intended Audience :: Developers
Classifier: License :: OSI Approved :: GNU Library or Lesser General Public License (LGPL)
Classifier: Operating System :: OS Independent
Classifier: Programming Language :: Python
Classifier: Topic :: Database :: Database Engines/Servers
Classifier: Topic :: Software Development :: Libraries :: Application Frameworks
